inferex/__init__.py
inferex/__main__.py
inferex/cli/__init__.py
inferex/cli/commands/deployments.py
inferex/cli/commands/pipelines.py
inferex/cli/commands/projects.py
inferex/cli/display.py
inferex/cli/terminal_format.py
inferex/cli/utils.py
inferex/common/project.py
inferex/decorator/__init__.py
inferex/decorator/inferex/__init__.py
inferex/decorator/inferex/decorators.py
inferex/sdk/__init__.py
inferex/sdk/exceptions.py
inferex/sdk/http.py
inferex/sdk/logs.py
inferex/sdk/resources/__init__.py
inferex/sdk/resources/base_models.py
inferex/sdk/resources/deployments.py
inferex/sdk/resources/logs.py
inferex/sdk/resources/pipelines.py
inferex/sdk/resources/projects.py
inferex/sdk/settings.py
inferex/sdk/validation.py
inferex-0.1.2.dist-info/entry_points.txt
inferex-0.1.2.dist-info/WHEEL
inferex-0.1.2.dist-info/METADATA
inferex-0.1.2.dist-info/RECORD
