Metadata-Version: 2.1
Name: inferex
Version: 0.1.2
Summary: Inferex CLI - Init, deploy and manage your projects on Inferex infrastructure
Author: Greg
Author-email: greg@inferex.com
Requires-Python: >=3.8,<4.0
Classifier: Programming Language :: Python :: 3
Classifier: Programming Language :: Python :: 3.8
Classifier: Programming Language :: Python :: 3.9
Classifier: Programming Language :: Python :: 3.10
Classifier: Programming Language :: Python :: 3.11
Requires-Dist: Cerberus (>=1.3.4,<2.0.0)
Requires-Dist: PyYAML (>=6.0,<7.0)
Requires-Dist: Pygments (>=2.12.0,<3.0.0)
Requires-Dist: click (>=8.1.3,<9.0.0)
Requires-Dist: dirhash (>=0.2.1,<0.3.0)
Requires-Dist: humanize (>=4.1.0,<5.0.0)
Requires-Dist: pydantic (>=1.9.2,<2.0.0)
Requires-Dist: python-dotenv (>=0.20.0,<0.21.0)
Requires-Dist: requests (>=2.28.0,<3.0.0)
Requires-Dist: requests-toolbelt (>=0.9.1,<0.10.0)
Requires-Dist: tabulate (>=0.8.9,<0.9.0)
Requires-Dist: tqdm (>=4.64.0,<5.0.0)
Requires-Dist: yaspin (>=2.1.0,<3.0.0)
